numpydoc/__init__.py
numpydoc/__main__.py
numpydoc/_version.py
numpydoc/cli.py
numpydoc/docscrape.py
numpydoc/docscrape_sphinx.py
numpydoc/numpydoc.py
numpydoc/validate.py
numpydoc/xref.py
numpydoc/hooks/__init__.py
numpydoc/hooks/utils.py
numpydoc/hooks/validate_docstrings.py
numpydoc/templates/numpydoc_docstring.rst
numpydoc/tests/test_docscrape.py
numpydoc/tests/test_full.py
numpydoc/tests/test_main.py
numpydoc/tests/test_numpydoc.py
numpydoc/tests/test_validate.py
numpydoc/tests/test_xref.py
numpydoc/tests/tinybuild/Makefile
numpydoc/tests/tinybuild/conf.py
numpydoc/tests/tinybuild/index.rst
numpydoc/tests/tinybuild/numpydoc_test_module.py
numpydoc-1.8.0.dist-info/LICENSE.txt
numpydoc-1.8.0.dist-info/METADATA
numpydoc-1.8.0.dist-info/WHEEL
numpydoc-1.8.0.dist-info/entry_points.txt
numpydoc-1.8.0.dist-info/top_level.txt
numpydoc-1.8.0.dist-info/RECORD
