Metadata-Version: 2.1
Name: numpydoc
Version: 1.8.0
Summary: Sphinx extension to support docstrings in Numpy format
Author-email: Pauli Virtanen and others <pav@iki.fi>
License: Copyright (C) 2008-2023 Stefan van der Walt <stefan@mentat.za.net>, Pauli Virtanen <pav@iki.fi>
Project-URL: Homepage, https://numpydoc.readthedocs.io
Project-URL: Source, https://github.com/numpy/numpydoc/
Keywords: sphinx,numpy
Classifier: Development Status :: 5 - Production/Stable
Classifier: Environment :: Plugins
Classifier: Intended Audience :: Developers
Classifier: License :: OSI Approved :: BSD License
Classifier: Operating System :: OS Independent
Classifier: Programming Language :: Python
Classifier: Programming Language :: Python :: 3
Classifier: Programming Language :: Python :: 3.9
Classifier: Programming Language :: Python :: 3.10
Classifier: Programming Language :: Python :: 3.11
Classifier: Programming Language :: Python :: 3.12
Classifier: Topic :: Documentation
Requires-Python: >=3.9
License-File: LICENSE.txt
Requires-Dist: sphinx>=6
Requires-Dist: tabulate>=0.8.10
Requires-Dist: tomli>=1.1.0; python_version < "3.11"
Provides-Extra: developer
Requires-Dist: pre-commit>=3.3; extra == "developer"
Requires-Dist: tomli; python_version < "3.11" and extra == "developer"
Provides-Extra: doc
Requires-Dist: numpy>=1.22; extra == "doc"
Requires-Dist: matplotlib>=3.5; extra == "doc"
Requires-Dist: pydata-sphinx-theme>=0.13.3; extra == "doc"
Requires-Dist: sphinx>=7; extra == "doc"
Requires-Dist: intersphinx_registry; extra == "doc"
Provides-Extra: test
Requires-Dist: pytest; extra == "test"
Requires-Dist: pytest-cov; extra == "test"
Requires-Dist: matplotlib; extra == "test"
